cfmtoolbox_rick_roll/__init__.py
cfmtoolbox_rick_roll-0.1.0.dist-info/METADATA
cfmtoolbox_rick_roll-0.1.0.dist-info/WHEEL
cfmtoolbox_rick_roll-0.1.0.dist-info/entry_points.txt
cfmtoolbox_rick_roll-0.1.0.dist-info/RECORD
